CHANGES.txt
DEPENDENCIES.txt
README.txt
bootstrap.py
buildout.cfg
setup.py
src/ks/__init__.py
src/ks.lib.egg-info/PKG-INFO
src/ks.lib.egg-info/SOURCES.txt
src/ks.lib.egg-info/dependency_links.txt
src/ks.lib.egg-info/namespace_packages.txt
src/ks.lib.egg-info/not-zip-safe
src/ks.lib.egg-info/requires.txt
src/ks.lib.egg-info/top_level.txt
src/ks/lib/__init__.py
src/ks/lib/datetime/__init__.py
src/ks/lib/datetime/utils.py
src/ks/lib/mailtemplate/README.txt
src/ks/lib/mailtemplate/TODO.txt
src/ks/lib/mailtemplate/__init__.py
src/ks/lib/mailtemplate/mailtemplate.py
src/ks/lib/pagetemplate/__init__.py
src/ks/lib/pagetemplate/viewpagetemplatestring.py
src/ks/lib/schema/__init__.py
src/ks/lib/schema/validation.py
src/ks/lib/scriptgetter/__init__.py
src/ks/lib/scriptgetter/scriptgetter.py
src/ks/lib/textguard/__init__.py
src/ks/lib/textguard/antimat.py
src/ks/lib/textguard/antiutf8
src/ks/lib/topolsort/INSTALL.txt
src/ks/lib/topolsort/README.txt
src/ks/lib/topolsort/TODO.txt
src/ks/lib/topolsort/__init__.py
src/ks/lib/topolsort/topolsort.py
src/ks/lib/topolsort/topolsort.txt
src/ks/lib/treenodeklp/INSTALL.txt
src/ks/lib/treenodeklp/README.txt
src/ks/lib/treenodeklp/TODO.txt
src/ks/lib/treenodeklp/__init__.py
src/ks/lib/treenodeklp/treenodeklp.py
src/ks/lib/treenodeklp/treenodeklp.txt
src/ks/lib/treenodeklp/tests/__init__.py
src/ks/lib/treenodeklp/tests/test_compare.py
src/ks/lib/tstypes/__init__.py
src/ks/lib/tstypes/tstypes.py